{
  "date": "2026-03-16",
  "quizzes": {
    "lv-easy": [
      {
        "levelClass": "lv-easy",
        "source": "2026.03.16 · 경제뉴스",
        "news_idx": 0,
        "context": "중동 지정학적 긴장이 고조되면서 국제유가가 큰 폭으로 올랐어요. 이렇게 되면 환율도 함께 움직이면서 우리 경제에 영향을 미친다고 해요.",
        "q": "기사에 따르면 NDF 원/달러 환율이 기록한 수치는?",
        "opts": [
          "1,502.50원",
          "1,352.50원",
          "1,250.50원",
          "1,752.50원"
        ],
        "ans": 0,
        "exp": "<strong>1,502.50원</strong>이 맞아요. 지정학적 리스크(중동 갈등)로 안전자산인 달러 수요가 늘어나면서 원화 가치가 하락했거든요. 원/달러 환율이 올라갈수록 수출 경쟁력은 높아지지만, 수입가격은 올라가는 구조예요.",
        "expert_detail": "<span class=\"expert-label\">🎓 박사의 한마디</span><p><strong>환율의 수급 메커니즘</strong>(환율은 수요와 공급으로 결정되는 상품이라는 뜻)이 오늘 기사에 잘 드러나있어요. 위험한 상황에서 투자자들이 달러를 더 사려고 하면 달러 가치가 올라가고, 상대적으로 원화는 약해지는 거거든요.</p><p>2008년 글로벌 금융위기 때도 마찬가지였어요. 리먼브라더스 파산 직후 원/달러 환율이 1,400원대에서 1,600원대로 급등했던 사건이 있었거든요. 당시 한국 기업들도 환율 변동으로 큰 타격을 입었던 상황이었어요.</p><p class=\"takeaway\">지정학적 리스크가 높아질수록 달러 수요 증가 → 원화 약세 → 환율 상승이라는 연쇄 구조를 이해하는 게 중요해요.</p>",
        "article_title": "100달러 넘은 국제유가…코스피 변동성 확대 지속하나",
        "article_url": "https://www.yna.co.kr/view/AKR20260316019100008?input=1195m"
      },
      {
        "levelClass": "lv-easy",
        "source": "2026.03.16 · 경제뉴스",
        "news_idx": 1,
        "context": "부동산 시장의 금리 인상이 계속되면서 가계의 부담이 커지고 있어요. 기사에서 언급된 한계 금리 수치를 찾아볼까요.",
        "q": "4대 은행 주택담보대출 금리 최고 수치는?",
        "opts": [
          "6.99%",
          "7.25%",
          "6.49%",
          "6.74%"
        ],
        "ans": 0,
        "exp": "기사에 따르면 <strong>연 6.99%</strong>까지 치솟았다고 보도됐어요. 금리가 오를수록 대출금을 받은 사람들의 월 상환액이 늘어나고, 이는 가계 소비 심리를 위축시키는 요인이 돼요.",
        "expert_detail": "<span class=\"expert-label\">🎓 박사의 한마디</span><p><strong>금리의 파급효과</strong>(한 경제 부문의 변화가 다른 부문으로 연쇄적으로 영향을 미친다는 뜻)를 생각해봐야 해요. 주택담보대출 금리가 올라가면, 이자 비용이 많아져서 소비할 돈이 줄어드는 거거든요.</p><p>2022년 미국 연방준비제도(Fed)가 기준금리를 급격히 올렸을 때도 비슷한 현상이 있었어요. 미국 주택 판매량이 급감했고, 이는 건설업과 가구·건자재 산업까지 영향을 주면서 경제 전체에 부정적 신호를 보냈거든요.</p><p class=\"takeaway\">높은 금리는 대출자의 이자 부담 증가 → 가계 소비 위축 → 경제 성장률 둔화로 이어지는 악순환을 만들어요.</p>",
        "article_title": "주담대 금리 7% 눈앞…유가·환율까지 3중고",
        "article_url": "https://news.tvchosun.com/site/data/html_dir/2026/03/16/2026031690009.html"
      },
      {
        "levelClass": "lv-easy",
        "source": "2026.03.16 · 경제뉴스",
        "news_idx": 0,
        "context": "국제유가가 100달러를 넘으면서 금융시장도 영향을 받고 있어요. 우리나라 증시는 어떤 변화를 보이고 있을까요?",
        "q": "기사에서 예상하는 코스피 시장의 변화는?",
        "opts": [
          "지속적 하락",
          "내 월급도 올라간다 🙏",
          "변동성의 확대",
          "강한 상승세"
        ],
        "ans": 2,
        "exp": "기사에 따르면 국제유가 상승이 <strong>코스피 변동성을 더욱 확대</strong>시킬 것으로 예상하고 있어요. 변동성 확대는 주가가 크게 오르내린다는 뜻이므로, 투자자들이 시장을 예측하기 어렵게 만들어요.",
        "expert_detail": "<span class=\"expert-label\">🎓 박사의 한마디</span><p><strong>변동성(volatility)</strong>은 자산 가격이 등락하는 정도를 나타내는 경제 지표에요. 변동성이 높으면 위험도 높아지기 때문에, 투자자들은 더 많은 보상(높은 수익률)을 요구하게 되거든요.</p><p>2011년 유럽 재정위기 당시를 보면, 코스피 변동성지수(VKOSPI)가 평상시 20~30 수준에서 70~80으로 급등했던 일이 있었어요. 이 기간 많은 개인투자자들이 손실을 입으면서 투자심리가 얼어붙었던 거였거든요.</p><p class=\"takeaway\">지정학적 리스크(중동 긴장)와 금리 불확실성이 겹치면서 주식시장의 변동성이 커지고, 이는 투자자의 판단을 어렵게 만들어요.</p>",
        "article_title": "100달러 넘은 국제유가…코스피 변동성 확대 지속하나",
        "article_url": "https://www.yna.co.kr/view/AKR20260316019100008?input=1195m"
      },
      {
        "levelClass": "lv-easy",
        "source": "2026.03.16 · 경제뉴스",
        "news_idx": 1,
        "context": "기사에서 언급된 '영끌족'이라는 신조어가 있어요. 부동산 시장의 금리 상승이 이들에게 미치는 영향을 생각해봐야 해요.",
        "q": "'영끌족'에게 금리 상승이 미치는 주요 영향은?",
        "opts": [
          "내 FICO 스코어가 올라간다 📈",
          "대출받기가 더 쉬워진다",
          "집값이 더 싸진다",
          "이자 부담 증가와 소비 심리 위축"
        ],
        "ans": 3,
        "exp": "기사에서 <strong>금리 상승이 가계의 이자 부담을 가중시키고 소비 심리를 위축</strong>시킨다고 분석했어요. 영끌족(영혼까지 끌어모아 대출받는 사람들)은 대출금이 크기 때문에 금리 변화에 더 민감하게 반응한답니다.",
        "expert_detail": "<span class=\"expert-label\">🎓 박사의 한마디</span><p><strong>대출승수 효과</strong>(차입금으로 투자할 때 원금 변화보다 손익 변화가 더 크다는 뜻)를 이해하면 좋아요. 영끌족처럼 많은 돈을 빌려서 집을 샀다면, 금리가 1% 올라갈 때 손해도 크거든요.</p><p>2019년 서울 부동산 광풍 당시 많은 사람들이 전세 자금이나 대출로 집을 샀는데, 2021년 이후 금리가 오르자 월상환액이 급증해서 파산한 가계들이 많았어요. 당시 신용카드 연체율도 함께 올라갔거든요.</p><p class=\"takeaway\">금리 상승은 빌린 돈이 많을수록 더 큰 타격을 주기 때문에, 영끌족의 경제 활동이 위축되고 이는 전체 경제 활력 저하로 이어져요.</p>",
        "article_title": "주담대 금리 7% 눈앞…유가·환율까지 3중고",
        "article_url": "https://news.tvchosun.com/site/data/html_dir/2026/03/16/2026031690009.html"
      },
      {
        "levelClass": "lv-easy",
        "source": "2026.03.16 · 경제뉴스",
        "news_idx": 0,
        "context": "중동 정세 악화가 국제유가를 올렸을 때 생기는 경제 현상을 알아볼까요. 전 세계 시장이 어떻게 반응하는지 살펴보는 거예요.",
        "q": "국제유가 상승이 아시아 시장을 먼저 흔드는 이유는?",
        "opts": [
          "아시아가 석유를 소비하는 유일한 지역이라서",
          "시간대 차이로 아시아 시장이 먼저 움직이기 때문",
          "유가는 아시아 시장에만 영향을 미쳐요",
          "아무 일도 안 생긴다 🤷"
        ],
        "ans": 1,
        "exp": "기사에 따르면 <strong>지난 주말 하르그섬 공격 후 아시아 시장이 먼저 급등 출발</strong>했다고 해요. 글로벌 금융시장은 24시간 돌아가는데, 시간대 차이로 인해 아시아 시장이 먼저 뉴스에 반응하게 되는 구조랍니다.",
        "expert_detail": "<span class=\"expert-label\">🎓 박사의 한마디</span><p><strong>글로벌 금융시장의 시간대 순환</strong>(뉴욕-런던-도쿄-싱가포르 순서로 이어지는 24시간 거래 구조)을 알면 시장을 이해하기 쉬워요. 미국 시간 주말 뉴스도 한국 시간으로는 이미 월요일 아침이거든요.</p><p>2001년 9월 11일 테러 직후를 보면, 서울 증시가 뉴욕 증시보다 먼저 급락했어요. 한국이 시간대상 먼저 개장했기 때문에, 공포 심리를 가장 먼저 반영했던 거였거든요.</p><p class=\"takeaway\">글로벌 뉴스는 시간대 순서대로 각 시장에 영향을 미치므로, 아시아 시장의 움직임이 다른 지역의 선행지표가 될 수 있어요.</p>",
        "article_title": "100달러 넘은 국제유가…코스피 변동성 확대 지속하나",
        "article_url": "https://www.yna.co.kr/view/AKR20260316019100008?input=1195m"
      },
      {
        "levelClass": "lv-easy",
        "source": "2026.03.16 · 경제뉴스",
        "news_idx": 1,
        "context": "기사에서 언급한 '3고 현상'이 우리 경제에 어떤 위기를 만들고 있는지 살펴봐요. 복합적 경제 어려움이 동시에 일어날 때 나타나는 현상이에요.",
        "q": "기사의 '3고 현상'에 포함되지 않는 것은?",
        "opts": [
          "환율 상승",
          "공급 부족",
          "유가 급등",
          "금리 상승"
        ],
        "ans": 1,
        "exp": "기사에서 언급한 <strong>3고 현상은 유가·환율·금리 상승</strong>이에요. 이 세 가지가 동시에 일어나면 기업의 생산비 증가, 가계의 부채 부담 증가, 수입가격 인상 등이 겹쳐서 경제가 어려워지는 거랍니다.",
        "expert_detail": "<span class=\"expert-label\">🎓 박사의 한마디</span><p><strong>스태그플레이션</strong>(경기 침체와 물가 상승이 동시에 일어나는 현상, 경제학자들이 가장 어려운 상황으로 꼽음)과 유사한 구조거든요. 기업은 수익이 안 나는데 비용만 올라가고, 가계는 이자 부담과 물가 부담을 동시에 받으니까요.</p><p>1970년대 오일쇼크 당시 미국이 대표적인 스태그플레이션을 겪었어요. 유가 급등으로 물가는 10% 이상 올랐는데, 경기는 마이너스 성장을 기록했거든요. 당시 실업률도 6%를 넘으면서 국민 생활이 정말 힘들었던 시대였어요.</p><p class=\"takeaway\">금리·유가·환율이 동시에 올라가는 '3고'는 기업과 가계 모두에게 타격을 주는 최악의 경제 상황이에요.</p>",
        "article_title": "주담대 금리 7% 눈앞…유가·환율까지 3중고",
        "article_url": "https://news.tvchosun.com/site/data/html_dir/2026/03/16/2026031690009.html"
      },
      {
        "levelClass": "lv-easy",
        "source": "2026.03.16 · 경제뉴스",
        "news_idx": 0,
        "context": "지정학적 긴장이 고조되면서 금융시장의 심리가 약해지고 있어요. 기사에서 투자자들의 심리 상태를 어떻게 표현했는지 살펴봐요.",
        "q": "현재 시장의 투자 심리를 가장 잘 설명하는 기사 표현은?",
        "opts": [
          "회복할 만한 재료가 부족하다",
          "좋은 뉴스가 많이 나오고 있다",
          "주가가 계속 올라간다 📈",
          "투자자들이 강한 확신을 가지고 있다"
        ],
        "ans": 0,
        "exp": "기사에서 <strong>'투자 심리를 회복할 만한 재료가 부족'</strong>하다고 표현했어요. 이는 투약자들이 긍정적인 경제 뉴스를 기다리고 있지만, 지정학적 리스크와 경제 불확실성이 계속되고 있다는 뜻이에요.",
        "expert_detail": "<span class=\"expert-label\">🎓 박사의 한마디</span><p><strong>동물 정신(Animal Spirits)</strong>(경제학자 케인즈가 말한 개념으로, 투자자의 심리와 기대감이 시장을 크게 좌우한다는 뜻)이 오늘날에도 중요해요. 실제 경제 지표가 나빴어도 투자자의 심리가 좋으면 주가는 오를 수 있거든요.</p><p>2008년 금융위기 직후 2009년은 경기가 바닥이었지만, 정부의 부양책과 낮은 금리에 투자자 심리가 회복되면서 주가가 오히려 올랐어요. 반대로 2020년 코로나 초기 몇 주간은 경제적 피해가 명확하지 않았는데도 공포 심리가 지배해서 주가가 급락했거든요.</p><p class=\"takeaway\">투자 심리의 회복 여부가 시장 방향을 결정하는 주요 요소이기 때문에, 기업이나 정부의 긍정적 신호와 뉴스가 아주 중요해요.</p>",
        "article_title": "100달러 넘은 국제유가…코스피 변동성 확대 지속하나",
        "article_url": "https://www.yna.co.kr/view/AKR20260316019100008?input=1195m"
      }
    ],
    "lv-mid": [
      {
        "levelClass": "lv-mid",
        "source": "2026.03.16 · 경제뉴스",
        "news_idx": 0,
        "context": "한국 증시에서 삼성전자와 SK하이닉스 같은 대형주의 영향력이 커지고 있어요. 이란 전쟁 이후 주가가 급락하면서 투자자들의 불안감도 높아지고 있습니다.",
        "q": "기사에 따르면 삼성전자·SK하이닉스가 코스피 시총에서 차지하는 비율은?",
        "opts": [
          "약 30%",
          "약 20%",
          "약 40%",
          "약 50%"
        ],
        "ans": 2,
        "exp": "<p>삼성전자와 SK하이닉스는 한국 증시의 <strong>'투톱' 대장주</strong>에요. 이 두 회사가 코스피 전체 시가총액의 <strong>40%에 육박</strong>하고 있다는 것은 시장 집중도가 매우 높다는 의미입니다.</p>",
        "expert_detail": "<span class=\"expert-label\">🎓 박사의 한마디</span><p><strong>시장 집중도(Market Concentration)</strong>는 소수의 기업이 시장의 대부분을 차지하는 정도를 나타내는 경제 지표예요. 집중도가 높을수록 시장이 불안정해질 수 있거든요. (마치 한 줄의 밧줄을 몇 사람이 잡고 있는 것처럼, 적은 수의 회사에 의존하면 위험해진다는 뜻이에요.)</p><p>실제로 1990년대 일본 버블 붕괴 당시 도쿄 증시의 상위 10개 기업이 지수의 30%를 차지했는데, 이들 주가가 동시에 폭락하면서 전체 시장이 극심한 변동성을 겪었습니다. 한국의 현재 상황도 비슷한 구조적 리스크를 안고 있어요.</p><p class=\"takeaway\">대형주 쏠림은 한 두 회사의 주가 변동이 곧 전체 시장의 변동으로 이어지는 <strong>'시스템 리스크'</strong>를 만든다는 게 핵심이에요.</p>",
        "article_title": "삼성전자·SK하이닉스 코스피 시총 40% 육박...널뛰는 장세에 ‘투톱’...",
        "article_url": "https://www.chosun.com/economy/money/2026/03/16/YQE2RJLGVVDLPDAHKNLZQO7IPY/?utm_source=naver&utm_medium=referral&utm_campaign=naver-news"
      },
      {
        "levelClass": "lv-mid",
        "source": "2026.03.16 · 경제뉴스",
        "news_idx": 0,
        "context": "최근 한국 증시에서 대형주들의 변동성이 심해지고 있어요. 한 날 삼성전자 주가가 크게 떨어지는 일도 발생했습니다.",
        "q": "기사에서 말하는 '롤러코스터 장세'의 주된 원인은?",
        "opts": [
          "금리 인상",
          "이란 전쟁",
          "환율 급등",
          "유가 하락"
        ],
        "ans": 1,
        "exp": "<p>기사에 따르면 <strong>이란 전쟁 이후</strong> 삼성전자 주가가 하루에만 11% 넘게 폭락하는 등 <strong>급격한 변동</strong>이 일어났어요. 이를 '롤러코스터 장세'라고 표현하고 있습니다.</p>",
        "expert_detail": "<span class=\"expert-label\">🎓 박사의 한마디</span><p><strong>지정학적 리스크(Geopolitical Risk)</strong>는 전쟁, 테러, 국제 분쟁 같은 정치적 사건이 경제에 미치는 불확실성을 뜻해요. (쉽게 말해 세계 어딘가에서 일어나는 국제 분쟁이 우리 지갑에도 영향을 미친다는 거죠.)</p><p>2001년 미국 9·11 테러 당시 뉴욕 증시의 S&P 500지수는 개장 후 하루에 약 5% 폭락했어요. 2022년 러시아-우크라이나 전쟁 당시도 유럽 증시에서 같은 날 10% 이상 급락한 일이 있었습니다.</p><p class=\"takeaway\">국제 분쟁은 예측 불가능하기 때문에 투자자들이 즉각 매도하면서 <strong>시장 변동성</strong>을 급증시키는 거예요.</p>",
        "article_title": "삼성전자·SK하이닉스 코스피 시총 40% 육박...널뛰는 장세에 ‘투톱’...",
        "article_url": "https://www.chosun.com/economy/money/2026/03/16/YQE2RJLGVVDLPDAHKNLZQO7IPY/?utm_source=naver&utm_medium=referral&utm_campaign=naver-news"
      },
      {
        "levelClass": "lv-mid",
        "source": "2026.03.16 · 경제뉴스",
        "news_idx": 1,
        "context": "최근 한국 경제가 여러 악재에 동시에 맞닥뜨리고 있어요. 유가 상승, 환율 상승, 관세 문제까지 겹쳐있습니다.",
        "q": "기사에서 산업계가 직면한 '퍼펙트스톰'을 이루는 세 가지는?",
        "opts": [
          "유가·금리·관세",
          "금리·환율·관세",
          "유가·환율·관세",
          "금리·유가·원화"
        ],
        "ans": 2,
        "exp": "<p>기사에 따르면 산업계가 맞닥뜨린 <strong>'퍼펙트스톰'</strong>은 <strong>유가·환율·관세</strong>가 동시에 악화되는 상황이에요. 이 세 가지가 동시에 일어나면서 수출 산업에 극심한 타격을 주고 있습니다.</p>",
        "expert_detail": "<span class=\"expert-label\">🎓 박사의 한마디</span><p><strong>퍼펙트스톰(Perfect Storm)</strong>은 경제학에서 여러 악재가 동시에 나타나 피해를 극대화하는 현상을 뜻해요. (마치 폭풍·해일·조수가 동시에 일어나는 최악의 상황처럼, 여러 위기가 한 번에 터진다는 뜻이거든요.)</p><p>2008년 글로벌 금융위기 당시 미국에서는 주택시장 붕괴, 은행 부실화, 신용경색이 동시에 발생했어요. 2022년 유럽도 에너지 위기, 인플레이션, 경기침체가 동시에 몰려오면서 역사적인 경제 위기를 맞았습니다.</p><p class=\"takeaway\">한국의 수출 산업도 유가 상승, 환율 약세, 관세 부과가 동시에 발생하면서 <strong>수익성과 경쟁력</strong>이 모두 악화될 위험에 처했다는 게 문제예요.</p>",
        "article_title": "유가·환율·관세 '삼중고'… 산업계 퍼펙트스톰 직면",
        "article_url": "http://www.metroseoul.co.kr/article/20260315500230"
      },
      {
        "levelClass": "lv-mid",
        "source": "2026.03.16 · 경제뉴스",
        "news_idx": 1,
        "context": "국제 유가와 환율이 상승하면서 수출 기업들의 비용이 늘어나고 있어요. 전문가들은 물가 상승 압력도 커질 것으로 예상하고 있습니다.",
        "q": "유가 급등 시 소비자에게 가장 직접적으로 영향 미치는 것은?",
        "opts": [
          "환율 하락",
          "주식 수익률 감소",
          "이자율 인상",
          "소비자물가 상승"
        ],
        "ans": 3,
        "exp": "<p>기사에서 한국개발연구원의 전문가는 <strong>유가 급등</strong>이 <strong>소비자물가 상승 압력</strong>을 만들 것으로 분석했어요. 유가가 오르면 배송비·제품 가격이 올라가기 때문입니다.</p>",
        "expert_detail": "<span class=\"expert-label\">🎓 박사의 한마디</span><p><strong>원유 가격 전가(Oil Price Pass-through)</strong>는 국제 유가 상승이 국내 물가 상승으로 이어지는 현상이에요. (원유는 자동차 휘발유, 난방유, 플라스틱 원료 등 거의 모든 산업에 쓰이거든요.)</p><p>2008년 유가가 배럴당 147달러까지 치솟았을 때 한국의 소비자물가 상승률은 연 4.7%까지 올라갔어요. 2022년 러시아 전쟁으로 유가가 급등했을 때도 한국 물가 상승률이 6%를 넘었습니다.</p><p class=\"takeaway\">유가 상승은 피할 수 없는 외부 충격이지만, 그것이 물가에 미치는 영향을 모니터링하고 대책을 세우는 것이 <strong>통화정책의 핵심</strong>이에요.</p>",
        "article_title": "유가·환율·관세 '삼중고'… 산업계 퍼펙트스톰 직면",
        "article_url": "http://www.metroseoul.co.kr/article/20260315500230"
      },
      {
        "levelClass": "lv-mid",
        "source": "2026.03.16 · 경제뉴스",
        "news_idx": 1,
        "context": "미국이 무역법 301조 조사를 시작하고 관세 부과 가능성을 높이고 있어요. 한국 같은 수출 국가에게는 큰 위협이 됩니다.",
        "q": "기사에서 한국 경제가 받을 수 있는 피해가 큰 이유는?",
        "opts": [
          "기술 수준이 낮기 때문",
          "수출에 의존하는 구조이기 때문",
          "내수 산업이 발달했기 때문",
          "금리가 높기 때문"
        ],
        "ans": 1,
        "exp": "<p>기사에 따르면 기사에서 '수출 중심인 한국 경제의 근간이 흔들릴 수 있다'고 명시했어요. <strong>관세 부과</strong>가 한국에 큰 타격을 주는 이유는 <strong>수출에 의존하는 경제 구조</strong> 때문입니다.</p>",
        "expert_detail": "<span class=\"expert-label\">🎓 박사의 한마디</span><p><strong>경제의 개방도(Trade Openness)</strong>는 수출과 수입이 GDP에서 차지하는 비중을 나타내는 지표예요. (한 나라의 경제가 국제 무역에 얼마나 의존하는지를 보는 척도라고 생각하면 돼요.)</p><p>한국의 수출 비중은 GDP의 약 40% 수준으로 매우 높은 편이에요. 반면 미국은 12% 정도로 훨씬 낮죠. 2010년대 미국 트럼프 행정부가 관세 전쟁을 시작했을 때 한국 기업들이 가장 큰 피해를 입은 이유도 이 때문이었습니다.</p><p class=\"takeaway\">관세는 수출 제품의 가격을 올려서 경쟁력을 떨어뜨리기 때문에, <strong>수출에 의존하는 나라일수록 관세 정책에 취약</strong>해요.</p>",
        "article_title": "유가·환율·관세 '삼중고'… 산업계 퍼펙트스톰 직면",
        "article_url": "http://www.metroseoul.co.kr/article/20260315500230"
      },
      {
        "levelClass": "lv-mid",
        "source": "2026.03.16 · 경제뉴스",
        "news_idx": 0,
        "context": "코스피에 쏠려있는 대형주의 비중이 매우 높아지고 있어요. 투자자들 사이에서 이를 우려하는 목소리가 커지고 있습니다.",
        "q": "기사에서 대형주 쏠림이 시장에 가져오는 영향은?",
        "opts": [
          "변동성 증가",
          "물가 안정",
          "변동성 감소",
          "주식 수익률 향상"
        ],
        "ans": 0,
        "exp": "<p>기사에 명시되어 있듯이 대형주 쏠림 현상은 <strong>시장의 변동성을 키우는 요인</strong>으로 작용할 수 있어요. 적은 수의 회사에 시장이 좌우되면 그들의 주가 변동이 극대화되기 때문입니다.</p>",
        "expert_detail": "<span class=\"expert-label\">🎓 박사의 한마디</span><p><strong>시장 유동성(Market Liquidity)</strong>은 시장이 얼마나 안정적으로 기능하는지를 보는 지표예요. (시장에 많은 참여자가 다양한 가격대에서 매매하면 급격한 변동을 완충할 수 있다는 뜻이거든요.)</p><p>2020년 코로나 위기 당시 미국 테크주(특히 FAANG 종목)가 시장의 과반을 차지했을 때, 이들 주가가 급락하자 전체 S&P 500지수가 하루에 12% 폭락하는 일이 발생했어요. 반면 중소형주들의 비중이 큰 날은 변동성이 훨씬 낮았습니다.</p><p class=\"takeaway\">다양한 산업·규모의 기업이 시장에 고르게 분포할 때 <strong>시장이 더 안정적</strong>이 되는 거예요.</p>",
        "article_title": "삼성전자·SK하이닉스 코스피 시총 40% 육박...널뛰는 장세에 ‘투톱’...",
        "article_url": "https://www.chosun.com/economy/money/2026/03/16/YQE2RJLGVVDLPDAHKNLZQO7IPY/?utm_source=naver&utm_medium=referral&utm_campaign=naver-news"
      },
      {
        "levelClass": "lv-mid",
        "source": "2026.03.16 · 경제뉴스",
        "news_idx": 1,
        "context": "원/달러 환율이 상승하고 있어요. 환율이 오르면 수출 기업들에게 어떤 영향을 미칠까요?",
        "q": "원/달러 환율 상승이 수출 기업에 주는 영향은?",
        "opts": [
          "수출품 가격 경쟁력 약화",
          "수출품 가격 경쟁력 향상",
          "수출 비용 절감",
          "수입 비용 감소"
        ],
        "ans": 0,
        "exp": "<p>기사에서는 <strong>원/달러 환율 상승</strong>이 산업계의 '퍼펙트스톰'을 이루는 악재로 꼽았어요. 환율이 오르면 외국인이 한국 제품을 사기 위해 더 많은 외화를 써야 하므로 <strong>경쟁력이 떨어집니다</strong>.</p>",
        "expert_detail": "<span class=\"expert-label\">🎓 박사의 한마디</span><p><strong>환율 효과(Exchange Rate Pass-through)</strong>는 환율 변동이 수출 가격에 미치는 영향을 뜻해요. (달러 당 원화 가치가 떨어지면, 같은 제품이 달러 기준으로는 더 비싸지는 거죠.)</p><p>2008년 글로벌 금융위기 때 달러화가 강해지면서 일본과 한국의 수출품 가격이 올라갔고, 미국과 유럽 고객들이 중국산 제품으로 돌아갔어요. 2022년 달러 강세 기간에도 미국 수입업자들이 더 저렴한 동남아 제품으로 구매처를 바꾼 사례가 많았습니다.</p><p class=\"takeaway\">환율이 오르면 수출 제품이 상대적으로 비싸지면서 <strong>가격 경쟁력이 약화</strong>되는 게 핵심이에요.</p>",
        "article_title": "유가·환율·관세 '삼중고'… 산업계 퍼펙트스톰 직면",
        "article_url": "http://www.metroseoul.co.kr/article/20260315500230"
      }
    ],
    "lv-hard": [
      {
        "levelClass": "lv-hard",
        "source": "2026.03.16 · 경제뉴스",
        "news_idx": 0,
        "context": "중동 전쟁 여파로 국제 유가가 급등하면서 국내 증시가 급등락을 반복하고 있어요. 이번 주 주요 이벤트들이 시장 심리에 큰 영향을 미칠 것으로 예상돼요.",
        "q": "기사에 따르면, 이번 주 한국 증시의 주요 변수는?",
        "opts": [
          "환율 변동과 금리 인상",
          "정부 정책 발표와 기업 분할",
          "FOMC 회의 결과와 엔비디아 GTC 발표",
          "부동산 경기 지표와 소비자물가"
        ],
        "ans": 2,
        "exp": "<strong>FOMC 회의 결과</strong>와 <strong>엔비디아의 GTC 발표</strong>가 시장의 주요 변수예요. 미국의 통화정책 방향과 AI 산업의 성장 모멘텀이 한국 증시에 미치는 파급력이 크거든요.",
        "expert_detail": "<span class=\"expert-label\">🎓 박사의 한마디</span><p><strong>금리 전염 효과(Interest Rate Contagion)</strong>는 한 국가의 금리 변화가 글로벌 자본 흐름을 통해 다른 국가에 영향을 미치는 현상이에요(즉, 미국 금리가 떨어지면 신흥국에 자금이 몰려온다는 뜻이거든요). 기사에서 FOMC가 중요한 이유는 바로 이것 때문이에요.</p><p>2023년 미국 연방준비제도가 금리 인상을 중단한다고 신호하자, 한국 증시는 3개월 만에 10% 이상 상승했던 사례가 있어요. 당시 AI 관련 기업들은 더욱 큰 상승률을 기록했답니다.</p><p class=\"takeaway\">🎯 <strong>미국 통화정책과 기술주 전망이 한국 증시의 상승 여력을 결정</strong>한다는 걸 기억하면 경제뉴스를 읽을 때 도움이 돼요!</p>",
        "article_title": "유가에 데인 韓증시, 이번주 FOMC·엔비디아 GTC 등 빅 이벤트 대기[주간...",
        "article_url": "https://www.sedaily.com/article/20019569?ref=naver"
      },
      {
        "levelClass": "lv-hard",
        "source": "2026.03.16 · 경제뉴스",
        "news_idx": 0,
        "context": "지정학적 불확실성 속에서도 국내 증시가 긍정적 신호를 찾고 있어요. 전문가들은 특정 산업과 기업 실적에 주목하고 있어요.",
        "q": "기사에 따르면 한국 증시 상승을 뒷받침할 요소는?",
        "opts": [
          "AI 투자 사이클과 기업 실적 모멘텀",
          "중동 전쟁의 조기 종료",
          "엔화 약세",
          "정부의 경기 부양 정책"
        ],
        "ans": 0,
        "exp": "<strong>AI 투자 사이클</strong>과 <strong>기업 실적 모멘텀</strong>이 확인되면 한국 증시가 상승 여력을 가질 수 있어요. 이는 지정학적 위험을 상쇄할 수 있는 긍정적 펀더멘털이 되거든요.",
        "expert_detail": "<span class=\"expert-label\">🎓 박사의 한마디</span><p><strong>모멘텀 투자 이론(Momentum Effect)</strong>은 좋은 실적이 나는 기업의 주가가 계속 올라가는 경향을 말해요(과거 좋은 성과가 미래에도 계속될 것이라 믿는 투자자들 때문이거든요). AI 기업들의 '실적 모멘텀'은 이 이론의 전형적인 예시예요.</p><p>2024년 엔비디아의 실적 발표 이후 나스닥 지수가 15% 상승했던 사례가 있어요. 당시 한국의 반도체 관련 기업들도 동반 상승했는데, 이것이 바로 '실적 모멘텀'의 힘이었답니다.</p><p class=\"takeaway\">🎯 <strong>기업 실적 개선이 지정학적 리스크를 극복하는 가장 강력한 버팀목</strong>이 될 수 있어요!</p>",
        "article_title": "유가에 데인 韓증시, 이번주 FOMC·엔비디아 GTC 등 빅 이벤트 대기[주간...",
        "article_url": "https://www.sedaily.com/article/20019569?ref=naver"
      },
      {
        "levelClass": "lv-hard",
        "source": "2026.03.16 · 경제뉴스",
        "news_idx": 1,
        "context": "금융당국이 대기업의 자본시장 활동을 제한하는 정책을 추진 중이에요. 이는 한국 증시의 국제 경쟁력 강화를 목표로 하고 있어요.",
        "q": "대기업 중복상장 금지의 목표는 무엇인가요?",
        "opts": [
          "기업 분할 강제",
          "재벌 개혁",
          "주가 조작 방지",
          "<strong>코리아 디스카운트</strong> 해소와 자본시장 선진화"
        ],
        "ans": 3,
        "exp": "금융당국은 <strong>코리아 디스카운트 해소</strong>와 <strong>자본시장 선진화</strong>를 위해 중복상장을 금지하려고 해요. 이는 한국 기업의 과소평가 문제를 개선하려는 정책이거든요.",
        "expert_detail": "<span class=\"expert-label\">🎓 박사의 한마디</span><p><strong>코리아 디스카운트(Korea Discount)</strong>는 같은 실적을 가진 한국 기업이 미국·일본 기업보다 낮게 평가받는 현상이에요(투자자들이 한국 시장을 덜 투명하고 리스크가 크다고 인식하기 때문이거든요). 중복상장 금지는 이 문제를 해결하려는 시도예요.</p><p>2010년대 일본도 비슷한 정책을 펼쳤어요. 당시 일본은 기업 지배구조 개선으로 3년 간 평균 주가수익비율(PER)을 선진국 평균에 가깝게 끌어올린 사례가 있답니다.</p><p class=\"takeaway\">🎯 <strong>한국 기업의 '작은 주가'를 '올바른 가치'로 재평가하는 구조 개혁</strong>이 이 정책의 핵심이에요!</p>",
        "article_title": "코리아 디스카운트 잡겠다…대기업 중복상장 사실상 봉쇄",
        "article_url": "https://www.sedaily.com/article/20019621?ref=naver"
      },
      {
        "levelClass": "lv-hard",
        "source": "2026.03.16 · 경제뉴스",
        "news_idx": 1,
        "context": "금융당국이 추진하는 중복상장 금지 정책에도 예외가 있어요. 정책의 세부 내용을 살펴볼 필요가 있어요.",
        "q": "중복상장 금지 정책의 예외 산업은?",
        "opts": [
          "국가첨단전략산업",
          "금융·보험업",
          "부동산·건설업",
          "소매·유통업"
        ],
        "ans": 0,
        "exp": "<strong>국가첨단전략산업</strong>은 중복상장 금지의 예외로 허용돼요. 다만 절차가 복잡해지므로 기업들의 실질적 부담은 커질 수 있어요.",
        "expert_detail": "<span class=\"expert-label\">🎓 박사의 한마디</span><p><strong>선별적 규제(Sectoral Regulation)</strong>는 특정 산업에만 다른 규칙을 적용하는 정책 수단이에요(국가가 전략적으로 중요한 산업은 보호하되, 나머지는 시장 규율에 맡긴다는 뜻이거든요). 반도체·바이오 같은 첨단산업을 예외로 둔 이유가 바로 이것이에요.</p><p>미국의 팹(FAB) 인센티브 정책도 비슷한 사례예요. 2022년 미국은 반도체 제조업체들에게만 550억 달러 지원금을 주면서 일반 기업은 제외했답니다.</p><p class=\"takeaway\">🎯 <strong>국가 경쟁력 있는 산업은 보호하되, 나머지는 엄격하게 규제한다</strong>는 전략적 접근이에요!</p>",
        "article_title": "코리아 디스카운트 잡겠다…대기업 중복상장 사실상 봉쇄",
        "article_url": "https://www.sedaily.com/article/20019621?ref=naver"
      },
      {
        "levelClass": "lv-hard",
        "source": "2026.03.16 · 경제뉴스",
        "news_idx": 1,
        "context": "중복상장 금지 정책이 시행되면 기업들의 자금 조달 방식이 달라질 수밖에 없어요. 전문가들은 이로 인한 부작용을 우려하고 있어요.",
        "q": "중복상장 금지로 예상되는 기업의 부담은?",
        "opts": [
          "주가 상승으로 인한 세금 증가",
          "기업 실적 부담 증가",
          "임직원 급여 삭감",
          "해외 진출 중단"
        ],
        "ans": 1,
        "exp": "기사에 따르면 중복상장 금지가 <strong>중견기업까지 영향</strong>을 미치면서 <strong>기업 실적 부담</strong>이 커질 수 있다고 분석돼요. 자금 조달의 다양성이 줄어들기 때문이거든요.",
        "expert_detail": "<span class=\"expert-label\">🎓 박사의 한마디</span><p><strong>자본조달 다양성(Financing Diversity)</strong>은 기업이 여러 경로에서 자금을 모을 수 있는 능력을 말해요(중복상장이 금지되면 이 경로가 닫혀 기업의 선택지가 줄어든다는 뜻이거든요). 특히 중견기업은 중복상장을 통해 쉽게 자금을 조달했어요.</p><p>1990년대 한국의 대우그룹이 중복상장을 통해 단기간에 300억 달러 이상을 조달했던 사례가 있어요. 이제 이런 '빠른 자금 조달 통로'가 막히는 거거든요.</p><p class=\"takeaway\">🎯 <strong>자금이 더 비싸고 더 어렵게 모이면, 결국 기업의 투자와 성장이 위축될 수 있다</strong>는 우려예요!</p>",
        "article_title": "코리아 디스카운트 잡겠다…대기업 중복상장 사실상 봉쇄",
        "article_url": "https://www.sedaily.com/article/20019621?ref=naver"
      },
      {
        "levelClass": "lv-hard",
        "source": "2026.03.16 · 경제뉴스",
        "news_idx": 0,
        "context": "국제 유가 급등이 한국 증시에 부정적 영향을 주고 있어요. 하지만 시장의 관심은 이미 다른 곳으로 움직이고 있어요.",
        "q": "유가 충격 속에서도 증시 상승을 기대하는 이유는?",
        "opts": [
          "AI 산업 성장성과 기업 펀더멘털",
          "유가가 이미 충분히 올랐음",
          "OPEC의 감산 약속",
          "중앙은행의 금리 인하"
        ],
        "ans": 0,
        "exp": "<strong>AI 산업의 성장성</strong>과 <strong>기업 실적 모멘텀</strong>이 지정학적 리스크(유가 급등)를 상쇄할 수 있다고 전문가들은 분석해요. 더 강력한 펀더멘털이 부정적 요인을 이기기 때문이에요.",
        "expert_detail": "<span class=\"expert-label\">🎓 박사의 한마디</span><p><strong>펀더멘털 vs 리스크 프리미엄(Fundamentals vs Risk Premium)</strong>은 기업의 실제 가치와 불확실성에 따른 할인율의 싸움이에요(펀더멘털이 강하면 리스크를 무시할 수 있다는 뜻이거든요). 기사의 핵심이 바로 이것이에요.</p><p>2008년 금융위기 당시에도 애플은 펀더멘털이 강했기 때문에 주가가 50% 떨어졌지만 3년 후 2배가 되었어요. 반면 펀더멘털이 약한 기업들은 회복하지 못했답니다.</p><p class=\"takeaway\">🎯 <strong>나쁜 뉴스도 좋은 기업 앞에서는 무력할 수 있다</strong>는 시장의 근본 법칙이에요!</p>",
        "article_title": "유가에 데인 韓증시, 이번주 FOMC·엔비디아 GTC 등 빅 이벤트 대기[주간...",
        "article_url": "https://www.sedaily.com/article/20019569?ref=naver"
      },
      {
        "levelClass": "lv-hard",
        "source": "2026.03.16 · 경제뉴스",
        "news_idx": 1,
        "context": "중복상장 금지 정책이 기업들의 절차를 복잡하게 만들 예정이에요. 예외 산업도 간단한 과정은 아닐 것 같아요.",
        "q": "중복상장 예외 허용 시 기업들이 거쳐야 할 절차는?",
        "opts": [
          "정부 부처 간담회만 진행",
          "주주총회 단순 의결",
          "CEO 승인만으로 진행",
          "이사회 결의와 공모주 청약 등 복잡한 절차"
        ],
        "ans": 3,
        "exp": "기사에 따르면 <strong>이사회 결의</strong>와 <strong>공모주 청약</strong> 등 <strong>절차가 복잡해질 수 있다</strong>고 언급돼요. 이는 기업의 중복상장 추진을 실질적으로 어렵게 만드는 규제 방식이에요.",
        "expert_detail": "<span class=\"expert-label\">🎓 박사의 한마디</span><p><strong>규제의 '절차적 부담(Procedural Burden)'</strong>은 명시적 금지보다 더 강력한 규제 수단이에요(법으로 막지는 않지만 과정을 복잡하게 해서 포기하도록 만든다는 뜻이거든요). 이를 '간접 규제' 또는 '실질적 규제'라고 불러요.</p><p>유럽연합의 환경 규제도 비슷해요. GDPR 같은 데이터 보호법은 기술회사들을 직접 금지하지 않지만, 준수 절차가 너무 복잡해서 자발적으로 사업을 축소하는 사례가 많았답니다.</p><p class=\"takeaway\">🎯 <strong>절차를 복잡하게 하는 것도 엄격한 금지만큼 효과적인 규제 수단</strong>이라는 정책 전문가의 관찰이에요!</p>",
        "article_title": "코리아 디스카운트 잡겠다…대기업 중복상장 사실상 봉쇄",
        "article_url": "https://www.sedaily.com/article/20019621?ref=naver"
      }
    ],
    "lv-expert": [
      {
        "levelClass": "lv-expert",
        "source": "2026.03.16 · 경제뉴스",
        "news_idx": 0,
        "context": "건설 경기 침체와 부동산 시장 위축이 심화되고 있어요. 이런 상황이 일용직 근로자들의 소득에 직접적인 영향을 미치고 있습니다.",
        "q": "임시·일용직 근로자의 월평균 소득은 얼마로 줄었나요?",
        "opts": [
          "174만원",
          "203만원",
          "225만원",
          "145만원"
        ],
        "ans": 0,
        "exp": "<strong>기사에 따르면 임시·일용직 근로자의 월평균 소득이 174만원</strong>으로 감소했어요. 이는 14년 만에 처음 나타난 감소 추세예요. 같은 기간 소비자물가가 약 16% 올랐는데 소득은 오히려 내려가서 실질 구매력이 크게 떨어졌습니다.",
        "expert_detail": "<span class=\"expert-label\">🎓 박사의 한마디</span><p><strong>경기순환(Business Cycle)</strong>이라는 경제학 개념이 있어요. 경제가 호황-침체-회복을 반복하는데, 현재 건설·부동산 부문이 침체 국면에 빠져있다는 뜻이거든요. 이때 노동 집약적 산업의 일용직 근로자들이 가장 먼저 피해를 입게 돼요.</p><p>2008년 글로벌 금융위기 당시 미국 건설업 일용직 근로자들의 실업률이 25%를 넘어갔던 사례가 있어요. 우리나라도 2008~2009년 건설 경기 침체로 비슷한 상황을 겪었었죠. 당시 임시·일용직 소득도 크게 감소했던 경험이 있습니다.</p><p class=\"takeaway\"><strong>건설경기 침체는 곧 가장 취약한 노동계층의 소득 감소로 직결</strong>되기 때문에, 경기 부양 정책이 중요해요.</p>",
        "article_title": "“정 안되면 노가다라도 뛰어야지”…그마저도 월급 깎인 174만원",
        "article_url": "https://www.mk.co.kr/article/11988611"
      },
      {
        "levelClass": "lv-expert",
        "source": "2026.03.16 · 경제뉴스",
        "news_idx": 1,
        "context": "같은 기간 전체 물가는 꾸준히 올랐는데 일용직 근로자의 소득은 반대 방향으로 움직였어요. 이는 경제 구조의 불균형을 보여주고 있습니다.",
        "q": "같은 기간 소비자물가 상승률은 약 몇 %였나요?",
        "opts": [
          "20%",
          "12%",
          "8%",
          "16%"
        ],
        "ans": 3,
        "exp": "<strong>소비자물가 상승률이 약 16%</strong>인데 일용직 소득은 오히려 감소했어요. 이는 근로자들의 <strong>실질소득(인플레이션을 반영한 실제 구매력)</strong>이 크게 악화됐다는 뜻입니다. 물가는 16% 올랐는데 월급은 줄어들었으니 생활비 부담이 심각해진 거예요.",
        "expert_detail": "<span class=\"expert-label\">🎓 박사의 한마디</span><p><strong>실질임금(Real Wage)</strong>은 명목임금에서 물가상승률을 뺀 개념이에요(즉, 실제로 살 수 있는 물건의 양을 뜻해요). 임금은 내려가는데 물가는 올라가면 실질임금은 이중으로 악화되는 거죠.</p><p>1970년대 스태그플레이션 시대 영국과 미국의 노동자들이 비슷한 고통을 겪었어요. 당시 임금은 정체하거나 감소했지만 물가는 두 자릿수로 올라가면서 근로자들의 삶의 질이 급격히 떨어졌습니다. 파업과 사회 갈등이 극심했던 시기였거든요.</p><p class=\"takeaway\"><strong>명목임금 감소 + 높은 물가 상승 = 실질생활수준의 심각한 악화</strong>라는 공식을 명심해야 해요.</p>",
        "article_title": "임시일용직 소득, 건설 한파로 14년만에 감소",
        "article_url": "https://www.mk.co.kr/article/11988557"
      },
      {
        "levelClass": "lv-expert",
        "source": "2026.03.16 · 경제뉴스",
        "news_idx": 1,
        "context": "건설과 부동산 부문이 경기 침체의 중심에 있어요. 특히 부동산업의 피해가 유독 심한 상황입니다.",
        "q": "부동산업 일용직 소득의 감소폭은 약 몇 %였나요?",
        "opts": [
          "6.2%",
          "14.5%",
          "11.1%",
          "8.8%"
        ],
        "ans": 2,
        "exp": "기사에 따르면 부동산업의 감소폭이 <strong>11.1%</strong>에 달했어요. 이는 전체 임시·일용직 감소율보다 훨씬 크다는 뜻이에요. <strong>부동산 시장 위축이 건설업계 일용직에 가장 직접적인 타격</strong>을 주고 있음을 보여줍니다.",
        "expert_detail": "<span class=\"expert-label\">🎓 박사의 한마디</span><p><strong>경기에 민감한 산업(Cyclical Industry)</strong>과 방어적 산업(Defensive Industry)이 있어요. 건설·부동산은 경기 변동에 극도로 민감해서 경기가 나빠지면 투자가 급감하고 일용직 일감이 사라지는 특성이 있거든요.</p><p>2011년 미국 부동산 버블 붕괴 이후 건설업 일용직 근로자들의 실직률이 30%를 넘었던 사례가 있어요. 한국도 2015년 부동산 경기 침체 때 비슷한 수준의 고통을 겪었었죠. 당시 건설 관련 일용직의 이탈이 심각했습니다.</p><p class=\"takeaway\"><strong>부동산업의 11.1% 감소는 건설경기 침체가 얼마나 심각한지를 가장 잘 보여주는 신호</strong>라고 할 수 있어요.</p>",
        "article_title": "임시일용직 소득, 건설 한파로 14년만에 감소",
        "article_url": "https://www.mk.co.kr/article/11988557"
      },
      {
        "levelClass": "lv-expert",
        "source": "2026.03.16 · 경제뉴스",
        "news_idx": 0,
        "context": "건설 경기 침체 상황에서 일용직 근로자들이 대체 일자리를 찾으려고 노력하고 있어요. 하지만 이마저도 쉽지 않은 상황입니다.",
        "q": "기사의 표현으로 봤을 때, 일용직이 찾는 '대체 일자리'의 특성은?",
        "opts": [
          "전문성이 높고 기술이 필요함",
          "높은 학력과 자격증 요구",
          "높은 급여 수준의 업종",
          "단순 육체노동으로 진입장벽 낮음"
        ],
        "ans": 3,
        "exp": "기사의 <strong>'노가다라도 뛰어야지'라는 표현</strong>이 핵심이에요. 이는 전문성 없는 단순 육체노동을 의미해요. 건설일감이 없어지니 더 낮은 수준의 일자리라도 찾아야 한다는 절박함을 드러낸 거죠. 이는 일용직 근로자의 <strong>취업 선택지가 극히 제한적</strong>임을 보여줍니다.",
        "expert_detail": "<span class=\"expert-label\">🎓 박사의 한마디</span><p><strong>노동시장 분할(Labor Market Segmentation)</strong이라는 개념이 있어요. 일용직 근로자들은 대부분 저숙련 부문에 집중되어 있어서, 경기가 나빠지면 같은 저숙련 부문 내에서만 일자리를 찾을 수밖에 없다는 뜻이거든요. 더 나은 직종으로 이동하기가 구조적으로 어렵다는 거예요.</p><p>1990년대 일본의 '잃어버린 10년' 경기침체 때 건설일용직들이 편의점, 배달, 청소 등 저임금 서비스업으로 대량 이동했었어요. 하지만 이런 이동도 소득 감소를 막지는 못했고, 경력 단절로 이어졌습니다.</p><p class=\"takeaway\"><strong>일용직 근로자는 경기 악화 시 '노가다'처럼 더 열악한 조건의 일로 밀려날 수밖에 없는 구조적 약자</strong>라는 점이 중요해요.</p>",
        "article_title": "“정 안되면 노가다라도 뛰어야지”…그마저도 월급 깎인 174만원",
        "article_url": "https://www.mk.co.kr/article/11988611"
      },
      {
        "levelClass": "lv-expert",
        "source": "2026.03.16 · 경제뉴스",
        "news_idx": 1,
        "context": "이번 소득 감소는 단순한 일시적 변동이 아니에요. 14년 만의 감소라는 사실이 의미하는 바가 큽니다.",
        "q": "14년 만에 처음 나타난 감소가 의미하는 바로 가장 적절한 것은?",
        "opts": [
          "임금 인상이 충분하다는 증거",
          "경기가 약간 둔화된 정도",
          "구조적 경기침체의 신호",
          "단순 계절적 변동"
        ],
        "ans": 2,
        "exp": "<strong>'14년 만의 감소'</strong>는 지난 14년간 계속 증가해왔다는 의미예요. 이렇게 오래 지속되던 상승 추세가 꺾였다는 것은 <strong>단순한 경기 둔화가 아니라 구조적 위기</strong>를 나타내요. 부동산 시장의 심각한 위축이 건설업 전반에 광범위하게 영향을 미치고 있다는 신호입니다.",
        "expert_detail": "<span class=\"expert-label\">🎓 박사의 한마디</span><p><strong>추세 변화(Trend Reversal)</strong>는 경제학에서 매우 중요한 신호예요. 14년간 지속된 증가 추세가 깨진다는 것은 근본적인 경제 구조 변화가 일어나고 있다는 뜻이거든요. 일시적 충격이 아니라 장기적 약세로 접어들었을 가능성이 높다는 겁니다.</p><p>2007년 미국 주택담보대출 위기도 처음엔 '일시적 조정'으로 치부됐지만, 몇 개월 뒤 글로벌 금융위기로 폭발했어요. 당시 미국 건설업 취업자 수가 3년에 걸쳐 200만 명 이상 감소했었거든요.</p><p class=\"takeaway\"><strong>14년 추세의 반전은 단순 경기 순환이 아닌 부동산·건설 산업의 구조적 위기 신호</strong>로 봐야 해요.</p>",
        "article_title": "임시일용직 소득, 건설 한파로 14년만에 감소",
        "article_url": "https://www.mk.co.kr/article/11988557"
      },
      {
        "levelClass": "lv-expert",
        "source": "2026.03.16 · 경제뉴스",
        "news_idx": 0,
        "context": "경제 어려움 속에서도 근로자들의 생활수준이 어떻게 변했는지 살펴보는 것이 중요해요. 물가와 임금의 관계를 분석해야 합니다.",
        "q": "소득 감소와 물가 상승이 동시에 일어날 때의 경제 현상은?",
        "opts": [
          "스태그플레이션",
          "디플레이션",
          "리플레이션",
          "인플레이션"
        ],
        "ans": 0,
        "exp": "소득은 내려가고 물가는 올라가는 상황을 <strong>스태그플레이션(Stagflation)</strong>이라고 해요. 이는 경제 성장 정체(Stagnation)와 물가 상승(Inflation)이 동시에 나타나는 최악의 상황이에요. <strong>근로자들은 고통이 가중</strong>되고 경제 회복이 매우 어려워집니다.",
        "expert_detail": "<span class=\"expert-label\">🎓 박사의 한마디</span><p><strong>스태그플레이션(Stagflation)</strong>은 경제학적으로 가장 다루기 어려운 상황이에요. 전통적인 경제 정책(금리 인상으로 물가 잡기 vs 금리 인하로 경기 부양)이 서로 충돌하기 때문이거든요. 둘 다 해결할 수 없는 딜레마 상황이라는 뜻이에요.</p><p>1970년대 오일쇼크로 인해 미국과 선진국들이 심각한 스태그플레이션을 겪었어요. 당시 미국은 물가는 12%까지 올랐는데 경제 성장률은 음수를 기록했거든요. 실업률도 9%를 넘어가면서 국민들의 생활이 극도로 악화됐습니다.</p><p class=\"takeaway\"><strong>임금 하락 + 물가 상승 = 스태그플레이션으로 근로자 삶의 질이 최악 수준</strong>까지 떨어질 수 있어요.</p>",
        "article_title": "“정 안되면 노가다라도 뛰어야지”…그마저도 월급 깎인 174만원",
        "article_url": "https://www.mk.co.kr/article/11988611"
      },
      {
        "levelClass": "lv-expert",
        "source": "2026.03.16 · 경제뉴스",
        "news_idx": 1,
        "context": "부동산 시장 위축과 건설 경기 침체가 연쇄적으로 영향을 미치고 있어요. 이런 연결고리를 이해하는 것이 경제 흐름을 파악하는 핵심입니다.",
        "q": "기사에서 보이는 '부동산→건설→일용직 소득'의 경제적 전파 메커니즘은?",
        "opts": [
          "산업연계효과",
          "수급불일치",
          "시장점유율 변화",
          "기술혁신의 영향"
        ],
        "ans": 0,
        "exp": "<strong>산업연계효과(Industrial Linkage Effect)</strong>는 한 산업의 변화가 관련 산업에 파급되는 현상이에요. 부동산 시장이 축소→건설 투자 감소→일용직 일감 부족→소득 감소로 이어지는 과정을 보여줍니다. <strong>경제의 한 부분의 충격이 연쇄적으로 퍼져나간다</strong>는 중요한 원리예요.",
        "expert_detail": "<span class=\"expert-label\">🎓 박사의 한마디</span><p><strong>산업연계분석(Input-Output Analysis)</strong이라는 경제학 분석 기법이 있어요. 각 산업이 얼마나 다른 산업에 영향을 미치는지 수량적으로 계산하는 거거든요. 부동산·건설은 가장 높은 수준의 산업연계효과를 갖는 산업 중 하나예요.</p><p>2018년 호주의 부동산 경기 침체 때 건설업 실직자 수가 3만 명 넘게 발생했고, 이게 철강·시멘트 등 관련 산업까지 연쇄적으로 타격을 입혔어요. 일용직 근로자들의 소득 감소도 이와 비슷한 맥락이거든요.</p><p class=\"takeaway\"><strong>부동산 위축 → 건설 투자 감소 → 일용직 소득 악화라는 산업 간 연쇄 효과</strong>를 이해하는 것이 경제 흐름 파악의 핵심이에요.</p>",
        "article_title": "임시일용직 소득, 건설 한파로 14년만에 감소",
        "article_url": "https://www.mk.co.kr/article/11988557"
      }
    ],
    "lv-master": [
      {
        "levelClass": "lv-master",
        "source": "2026.03.16 · 경제뉴스",
        "news_idx": 0,
        "context": "중동 지역의 군사적 충돌로 글로벌 금융시장이 요동치고 있어요. 한국은행에 따르면 원/달러 환율이 외환위기 이후 최고 수준까지 치솟았습니다.",
        "q": "기사에 따르면 13일 원·달러 환율 마감가는?",
        "opts": [
          "1,510.2원",
          "1,500.0원",
          "1,493.7원",
          "1,480.5원"
        ],
        "ans": 2,
        "exp": "<strong>정답은 1,493.7원</strong>이에요. 이는 전 거래일보다 12.5원 오른 수치로, 외환위기 이후 최고치 수준을 기록한 것으로 보도됐습니다. 중동 리스크가 원화 약세의 주요 원인이었어요.",
        "expert_detail": "<span class=\"expert-label\">🎓 박사의 한마디</span><p><strong>공포지수(Risk-Off 현상)</strong>란 글로벌 불확실성이 높아질 때 투자자들이 위험자산을 회피하고 안전자산으로 몰리는 현상입니다(이를 '리스크 오프'라고 불러요). 이 때 신흥국 통화인 원화는 투자자들의 회피 대상이 되면서 급락하게 되거든요.</p><p>1997년 아시아 금융위기 당시 한국 원/달러 환율이 1,900원까지 치솟았던 것이 대표 사례예요. 당시에도 국제 금융시장의 불확실성이 증가하면서 달러 선호 현상이 심화되었습니다.</p><p class=\"takeaway\">오늘날 중동 분쟁도 같은 맥락에서 원화가 주요국 중 가장 큰 폭으로 하락하게 만드는 거예요.</p>",
        "article_title": "1500원 다시 뚫린 환율… 중동 리스크에 원화 낙폭 주요국 최상위",
        "article_url": "https://www.hankookilbo.com/news/article/A2026031510490004226?did=NA"
      },
      {
        "levelClass": "lv-master",
        "source": "2026.03.16 · 경제뉴스",
        "news_idx": 1,
        "context": "미국과 이란의 군사적 충돌이 장기화될 가능성이 높아지고 있어요. 이런 상황에서 물가 안정을 위한 중앙은행의 역할이 더욱 중요해지고 있습니다.",
        "q": "기사에서 언급한 이창용 총재의 임기 만료 시점은?",
        "opts": [
          "5월",
          "2월",
          "4월",
          "3월"
        ],
        "ans": 2,
        "exp": "<strong>정답은 4월</strong>이에요. 이창용 한국은행 총재의 임기가 4월에 만료되는데, 대인플레이션 우려가 커지는 상황에서 차기 총재 인선이 중요한 시점입니다. 중앙은행의 독립성이 물가 안정을 좌우할 수 있기 때문이에요.",
        "expert_detail": "<span class=\"expert-label\">🎓 박사의 한마디</span><p><strong>지정학적 리스크에 따른 스태그플레이션(stagflation)</strong>은 경기 침체와 물가 상승이 동시에 일어나는 현상입니다(경제는 안 좋은데 물가는 오른다는 뜻이거든요). 유가 급등이 에너지 비용을 높이면서 물가를 상승시키는 동시에 경기를 악화시키는 악순환이 생기는 거예요.</p><p>1970년대 오일쇼크 때 미국이 겪은 경험이 전형적이에요. 당시 유가가 배럴당 3달러에서 12달러로 급등하면서 인플레이션이 10%를 넘었고, 동시에 경제성장률은 마이너스가 되었습니다.</p><p class=\"takeaway\">오늘날 중동 분쟁도 유가 상승→물가 압력 증가→경기 부양 필요의 딜레마를 만들고 있어서, 독립적인 중앙은행 리더십이 결정적이에요.</p>",
        "article_title": "미-이란 전쟁발 대인플레이션(GI) 우려…차기 한국은행 총재는[한상춘...",
        "article_url": "https://magazine.hankyung.com/business/article/202603114917b"
      },
      {
        "levelClass": "lv-master",
        "source": "2026.03.16 · 경제뉴스",
        "news_idx": 2,
        "context": "국제유가가 100달러를 넘으면서 금융시장 불안이 가중되고 있어요. 금융위원회는 시장 안정에 대비해 채권시장안정펀드 운용 규모를 늘리기로 결정했습니다.",
        "q": "기사에 따르면 채안펀드 현재 최대 운용 규모는?",
        "opts": [
          "15조원",
          "20조원",
          "10조원",
          "30조원"
        ],
        "ans": 1,
        "exp": "<strong>정답은 20조원</strong>이에요. 금융위원회는 상황 악화 시 이 규모에서 최소 10조원을 추가로 늘리는 방안을 논의했습니다. 이는 금융시장의 유동성 부족 사태에 선제적으로 대응하려는 조치예요.",
        "expert_detail": "<span class=\"expert-label\">🎓 박사의 한마디</span><p><strong>유동성 함정(Liquidity Trap)</strong>은 시장에 돈이 많아도 사람들이 안 쓰거나 투자하지 않아 경제가 움직이지 않는 상태입니다(마치 물이 담긴 그릇이 기울어져도 물이 흘러내리지 않는 것처럼요). 불확실성이 높을 때 시장 참여자들이 자금을 보유하기만 하므로, 정부가 직접 시장에 유동성을 공급해야 해요.</p><p>2008년 글로벌 금융위기 때 미국 연방준비제도(Fed)가 양적완화(QE)로 시장에 막대한 자금을 공급했던 것이 대표 사례입니다. 당시 미국 장기금리가 제로 수준으로 떨어졌는데도 경제가 움직이지 않자, Fed는 장기채권을 직접 매입했거든요.</p><p class=\"takeaway\">한국도 중동 분쟁으로 인한 자금경색 우려에 '시장 소방수' 역할을 할 채안펀드를 확충하는 거예요.</p>",
        "article_title": "국제유가 100달러 넘자, 환율 장중 1500원 다시 돌파",
        "article_url": "https://www.donga.com/news/Inter/article/all/20260316/133535389/2"
      },
      {
        "levelClass": "lv-master",
        "source": "2026.03.16 · 경제뉴스",
        "news_idx": 3,
        "context": "원화가 주요국 통화 대비 가장 큰 폭으로 약세를 기록하고 있어요. 기사에 따르면 이달 원·달러 환율 평균이 역사적 고점을 경신했습니다.",
        "q": "이달 평균 원·달러 환율이 넘어간 수준은?",
        "opts": [
          "1,470원",
          "1,400원",
          "1,500원",
          "1,450원"
        ],
        "ans": 0,
        "exp": "<strong>정답은 1,470원</strong>을 넘은 수준이에요. 이는 외환위기 이후 최고치를 기록한 것으로, 원화 약세의 심각성을 보여줍니다. 중동 리스크가 장기화할 경우 1,500원 고착화 우려가 커지고 있어요.",
        "expert_detail": "<span class=\"expert-label\">🎓 박사의 한마디</span><p><strong>구매력평가설(PPP, Purchasing Power Parity)</strong>은 환율이 두 나라 물가 수준의 차이에 따라 결정된다는 이론입니다(한국 물가가 미국 대비 떨어지면 원화 가치도 떨어진다는 뜻이거든요). 하지만 단기적으로는 심리, 정치 리스크, 자본 이동 같은 요소들이 환율을 크게 흔들어요.</p><p>1997년 IMF 외환위기 당시 한국 원/달러 환율이 몇 개월 만에 900원에서 1,900원으로 2배 이상 떨어졌어요. 이는 PPP 이론으로는 설명할 수 없는 급격한 자본 이탈 때문이었습니다.</p><p class=\"takeaway\">오늘날 중동 분쟁도 마찬가지로 단기 심리 요인이 강해서 환율이 빠르게 움직이는 거고, 이게 고착화되는 게 가장 무서운 상황이에요.</p>",
        "article_title": "원화 낙폭 주요국 최대… 환율 1500원 또 뚫려 고착화 우려 [美·이란 전...",
        "article_url": "https://www.segye.com/newsView/20260315509438?OutUrl=naver"
      },
      {
        "levelClass": "lv-master",
        "source": "2026.03.16 · 경제뉴스",
        "news_idx": 4,
        "context": "중동 군사 분쟁의 영향이 원화뿐 아니라 코스피까지 미치고 있어요. 전문가들은 원화와 코스피 동시 하락이 유독 큰 이유를 분석하고 있습니다.",
        "q": "원화와 코스피가 동시에 큰 폭 하락하는 현상의 주요 원인은?",
        "opts": [
          "국내 금리 인상",
          "글로벌 자금 이탈",
          "수출 감소",
          "정부 경기 부양 부족"
        ],
        "ans": 1,
        "exp": "<strong>글로벌 자금 이탈</strong>이 핵심이에요. 중동 리스크로 불확실성이 높아지면 글로벌 투자자들이 신흥국 주식(코스피)을 팔고 달러로 환전하면서(즉, 원화를 팔고) 동시에 환율이 올라요. 이것이 원화 약세와 주가 하락을 동시에 초래하는 메커니즘이에요.",
        "expert_detail": "<span class=\"expert-label\">🎓 박사의 한마디</span><p><strong>포트폴리오 이론(Portfolio Theory)</strong>은 투자자가 여러 자산에 분산 투자하되, 위험이 높아지면 위험 자산 비중을 줄인다는 이론입니다(불확실할 때는 안전자산 비중을 늘린다는 뜻이거든요). 신흥국 주식은 선진국 채권보다 위험이 크므로, 리스크 오프 상황에서 가장 먼저 팔려요.</p><p>2011년 유럽 재정위기 때 한국 코스피가 1,600선까지 떨어졌던 것이 사례예요. 당시 글로벌 투자자들이 신흥국 자산을 대량 매도했고, 동시에 안전자산인 미국채 수익률이 크게 떨어졌습니다.</p><p class=\"takeaway\">오늘날도 마찬가지로 중동 불확실성이 높아지면 글로벌 투자자들이 신흥국 주식을 팔면서 코스피와 원화가 동시에 약해지는 거예요.</p>",
        "article_title": "이란 전쟁에 유독 떨어진 원화 가치-코스피…도대체 왜",
        "article_url": "https://www.donga.com/news/Economy/article/all/20260315/133532954/1"
      },
      {
        "levelClass": "lv-master",
        "source": "2026.03.16 · 경제뉴스",
        "news_idx": 5,
        "context": "중동 분쟁 장기화 우려 속에서 물가 상승과 금리 인상이 맞물릴 가능성이 제기되고 있어요. 정부는 금융시장 불안에 사전 대응하고 있습니다.",
        "q": "중동 분쟁 장기화 시 물가와 금리의 악순환 고리는?",
        "opts": [
          "금리↑→수출감소→경기악화→물가↓",
          "환율↑→수입가격↑→물가↑→임금인상→물가↑",
          "유가↑→물가↑→금리↑→자금경색",
          "물가↑→금리↑→원화강→경기악화"
        ],
        "ans": 2,
        "exp": "<strong>기사의 핵심 파급경로는 유가↑→물가↑→금리↑→자금경색</strong>이에요. 유가 100달러 돌파로 에너지 수입 비용이 올라가면 물가가 오르고, 중앙은행이 이를 잡으려 금리를 올리면 차입 비용이 높아져 시중 자금이 경색될 수 있어요. 채안펀드 확충이 이 악순환 차단을 목표로 하고 있습니다.",
        "expert_detail": "<span class=\"expert-label\">🎓 박사의 한마디</span><p><strong>자산가격효과(Wealth Effect)</strong는 금리 인상으로 자산 가격(주식, 부동산)이 떨어지면 국민이 더 가난해진 것처럼 느껴 소비를 줄이는 현상입니다(내 집값이 떨어지면 기분이 안 좋아서 돈을 덜 쓰는 것처럼요). 금리 인상은 통화가 비싸지므로, 결국 소비와 투자 의욕을 꺾어요.</p><p>2022년 미국 연준의 급격한 금리 인상(0→4.25~4.5%)이 나스닥지수를 33% 하락시킨 것이 대표 사례예요. 당시 고금리로 기술주의 미래 현금흐름 가치가 하락하면서 주가가 붕괴했습니다.</p><p class=\"takeaway\">오늘날 한국도 유가 상승으로 물가가 오르면 한은이 금리를 올릴 수밖에 없는데, 이것이 주가와 부동산 시장을 동시에 위축시키고 최종적으로 경기를 악화시킬 수 있거든요.</p>",
        "article_title": "중동발 자금경색 대비…‘시장 소방수’ 채안펀드 확충 추진",
        "article_url": "https://www.segye.com/newsView/20260315504875?OutUrl=naver"
      },
      {
        "levelClass": "lv-master",
        "source": "2026.03.16 · 경제뉴스",
        "news_idx": 5,
        "context": "원/달러 환율이 1,495.5원까지 상승하면서 중동 분쟁의 경제적 파장이 가시화되고 있어요. 각 부처는 시장 안정을 위해 제각기 정책을 준비하고 있습니다.",
        "q": "현 상황에서 '시장 소방수'로 불리는 도구는?",
        "opts": [
          "금리 인하",
          "환율 개입",
          "채권시장안정펀드",
          "기준금리 조정"
        ],
        "ans": 2,
        "exp": "<strong>채권시장안정펀드(채안펀드)</strong>가 기사에서 '시장 소방수'로 표현됐어요. 이 펀드는 시장의 일시적 자금 경색에 대응해 채권을 매입하고 유동성을 공급하는 역할을 해요. 중동 분쟁으로 금융시장 불안이 심화될 때 채권 가격 급락을 방지하고 자금난을 해소하는 버팀목이 됩니다.",
        "expert_detail": "<span class=\"expert-label\">🎓 박사의 한마디</span><p><strong>신용경색(Credit Crunch)</strong>은 은행과 금융기관들이 위험을 피해 대출을 급격히 축소하는 현상입니다(금융기관들이 '나 위험해'라고 생각해서 돈을 안 빌려준다는 뜻이거든요). 이 때 정상적인 기업까지 자금을 구하기 어려워져 경제가 급격히 악화돼요.</p><p>2008년 리먼브라더스 파산 직후 미국 금융시장이 극도로 경색되자, 미국 재무부가 '문제 자산 구제 프로그램(TARP)'으로 7,000억 달러를 투입해 은행권 자금난을 풀었어요. 이것이 금융 붕괴를 막은 결정적 조치였습니다.</p><p class=\"takeaway\">한국의 채안펀드도 같은 맥락에서 시장 참여자들의 '자금 걱정'을 덜어주고 채권 가격 폭락을 방지함으로써 금융시장 안정을 지키는 거예요.</p>",
        "article_title": "중동발 자금경색 대비…‘시장 소방수’ 채안펀드 확충 추진",
        "article_url": "https://www.segye.com/newsView/20260315504875?OutUrl=naver"
      }
    ]
  }
}